COPYING
DEVELOPMENT
MANIFEST.in
NEWS
README
THANKS
TODO
changelog
ez_setup.py
pylintrc
setup.cfg
setup.py
characterdb/README
characterdb/favicon.ico
characterdb/favicon.svg
characterdb/logo.png
characterdb/logo.svg
cjklib/__init__.py
cjklib/characterlookup.py
cjklib/cjklib.conf
cjklib/cjklib.db
cjklib/cjknife.py
cjklib/dbconnector.py
cjklib/exception.py
cjklib/util.py
cjklib.egg-info/PKG-INFO
cjklib.egg-info/SOURCES.txt
cjklib.egg-info/dependency_links.txt
cjklib.egg-info/entry_points.txt
cjklib.egg-info/requires.txt
cjklib.egg-info/top_level.txt
cjklib/build/__init__.py
cjklib/build/builder.py
cjklib/build/cli.py
cjklib/data/cantoneseipainitialfinal.csv
cjklib/data/cantoneseipainitialfinal.sql
cjklib/data/cantoneseyaleinitialnucleuscoda.csv
cjklib/data/cantoneseyaleinitialnucleuscoda.sql
cjklib/data/cantoneseyalesyllables.csv
cjklib/data/cantoneseyalesyllables.sql
cjklib/data/characterdecomposition.csv
cjklib/data/characterdecomposition.sql
cjklib/data/charactershanghaineseipa.csv
cjklib/data/charactershanghaineseipa.sql
cjklib/data/grabbreviation.csv
cjklib/data/grabbreviation.sql
cjklib/data/grrhotacisedfinals.csv
cjklib/data/grrhotacisedfinals.sql
cjklib/data/grsyllables.csv
cjklib/data/grsyllables.sql
cjklib/data/jyutpinginitialfinal.csv
cjklib/data/jyutpinginitialfinal.sql
cjklib/data/jyutpingipamapping.csv
cjklib/data/jyutpingipamapping.sql
cjklib/data/jyutpingsyllables.csv
cjklib/data/jyutpingsyllables.sql
cjklib/data/jyutpingyalemapping.csv
cjklib/data/jyutpingyalemapping.sql
cjklib/data/kangxiradical.csv
cjklib/data/kangxiradical.sql
cjklib/data/kangxiradicalisolatedcharacter.csv
cjklib/data/kangxiradicalisolatedcharacter.sql
cjklib/data/localecharacterglyph.csv
cjklib/data/localecharacterglyph.sql
cjklib/data/mandarinipainitialfinal.csv
cjklib/data/mandarinipainitialfinal.sql
cjklib/data/pinyinbraillefinalmapping.csv
cjklib/data/pinyinbraillefinalmapping.sql
cjklib/data/pinyinbrailleinitialmapping.csv
cjklib/data/pinyinbrailleinitialmapping.sql
cjklib/data/pinyingrmapping.csv
cjklib/data/pinyingrmapping.sql
cjklib/data/pinyininitialfinal.csv
cjklib/data/pinyininitialfinal.sql
cjklib/data/pinyinipamapping.csv
